<Lems xmlns="http://www.neuroml.org/lems/0.7.4"
      xmlns:xsi="http://www.w3.org/2001/XMLSchema-instance"
      xsi:schemaLocation="http://www.neuroml.org/lems/0.7.4 ../../LEMS/Schemas/LEMS/LEMS_v0.7.4.xsd" >

    <ComponentType  name="rateCell"
                    extends="baseCellMembPot"
                    description="...">


        <Parameter name="Vth" dimension="voltage"/>
        <Parameter name="Vr" dimension="voltage"/>
        <Parameter name="Vl" dimension="voltage"/>
        <Parameter name="Vscale" dimension="voltage"/>
        <Parameter name="r0" dimension="per_time"/>
        <Parameter name="V0" dimension="voltage"/>

        <Parameter name="gl" dimension="conductance"/>

        <Parameter name="tau" dimension="time"/>
        <Parameter name="tau_r" dimension="time"/>

        <Attachments name="synapses" type="basePointCurrent"/>

        <Exposure name="r" dimension="per_time"/>
        <Exposure name="iSyn" dimension="current"/>
        <Exposure name="V" dimension="voltage"/>
        <Exposure name="f" dimension="per_time"/>
        <Exposure name="r0" dimension="per_time"/>


        <Dynamics>

            <OnStart>
                <StateAssignment variable="r" value="r0"/>
            </OnStart>

            <StateVariable name="v" dimension="voltage" exposure="v"/>
            <StateVariable name="r" dimension="per_time" exposure="r" description="Rate..."/>

            <DerivedVariable name="iSyn" dimension="current" exposure="iSyn" select="synapses[*]/i" reduce="add" />

            <DerivedVariable name="V" dimension="voltage" exposure="V" value="Vl + (iSyn)/gl"/>

            <DerivedVariable name="f" dimension="per_time" exposure="f" value="( (V-Vth)/(tau*(Vth-Vr)) ) * (1/(1-exp(-1*(V-Vth)/Vscale)))"/>

            <TimeDerivative variable="r" value="(-1*r + f)/tau_r"/>


            <OnCondition test="V .gt. Vth">
                <EventOut port="spike"/>
            </OnCondition>

        </Dynamics>

    </ComponentType>


    <ComponentType name="rateSynapse"
                   extends="baseGradedSynapse"
                   description="...">

        <Property name="weight" dimension="none" defaultValue="1"/>

        <Constant name="MSEC" dimension="time" value="1ms"/>
        <Constant name="PAMP" dimension="current" value="1nA"/>

        <Exposure name="i" dimension="current"/>

        <Requirement name="r" dimension="per_time"/>

        <InstanceRequirement name="peer" type="rateSynapse"/>

        <Dynamics>
            <DerivedVariable name="rpeer" dimension="per_time" select="peer/r"/>
            <DerivedVariable name="i" exposure="i"  value="weight * MSEC * PAMP * rpeer"/>
        </Dynamics>
    </ComponentType>

</Lems>
